riminder/__init__.py
riminder/base64Wrapper.py
riminder/bytesutils.py
riminder/filter.py
riminder/hmacutils.py
riminder/profile.py
riminder/riminder.py
riminder/source.py
riminder/webhook.py
riminder-1.4.2.dist-info/LICENSE.txt
riminder-1.4.2.dist-info/METADATA
riminder-1.4.2.dist-info/WHEEL
riminder-1.4.2.dist-info/top_level.txt
riminder-1.4.2.dist-info/RECORD
