Metadata-Version: 2.1
Name: riminder
Version: 1.4.2
Summary: python riminder riminder api package
Home-page: https://github.com/Riminder/python-riminder-api
Author: mnouayti
Author-email: contact@rimider.net
License: MIT
Platform: UNKNOWN
Requires-Python: >=3.5
Requires-Dist: requests
Requires-Dist: python-magic
